is_palindrome_asfa
