Metadata-Version: 1.0
Name: check-palindrome-asfa
Version: 0.0.2
Summary: This is a palindrome checking
Home-page: https://jdfbjdbvkj
Author: Mohammed Abdul Raheem
Author-email: UNKNOWN
License: MIT
Keywords: palindrome,python pallindrome
Platform: UNKNOWN
